conciliacaocore/__init__.py
conciliacaocore/config.py
conciliacaocore/database.py
conciliacaocore/date_utils.py
conciliacaocore/logger.py
conciliacaocore/spark.py
conciliacaocore-0.0.7.dist-info/LICENSE
conciliacaocore-0.0.7.dist-info/METADATA
conciliacaocore-0.0.7.dist-info/WHEEL
conciliacaocore-0.0.7.dist-info/top_level.txt
conciliacaocore-0.0.7.dist-info/RECORD
