Metadata-Version: 2.1
Name: conciliacaocore
Version: 0.0.7
Summary: Utilitários comuns para projetos de conciliação
Home-page: https://gitlab.com/sdna-team/okto/sdna-conciliacao
Author: Fernando Miranda Calil
Author-email: fcalil@sdnadigital.com
License: UNKNOWN
Platform: UNKNOWN
Classifier: Programming Language :: Python :: 3
Classifier: License :: OSI Approved :: MIT License
Classifier: Operating System :: OS Independent
Requires-Python: >=3.9
License-File: LICENSE
Requires-Dist: psycopg2-binary (>=2.9.5)
Requires-Dist: pyspark (>=3.3.2)
